checkcrontab/__init__.py
checkcrontab/__main__.py
checkcrontab/checker.py
checkcrontab/logger.py
checkcrontab/main.py
checkcrontab-0.0.12.dist-info/licenses/LICENSE
checkcrontab-0.0.12.dist-info/METADATA
checkcrontab-0.0.12.dist-info/WHEEL
checkcrontab-0.0.12.dist-info/entry_points.txt
checkcrontab-0.0.12.dist-info/top_level.txt
checkcrontab-0.0.12.dist-info/RECORD
