Metadata-Version: 2.4
Name: checkcrontab
Version: 0.0.12
Summary: A Python3 script for checking syntax and correctness of crontab files
Author-email: Aleksandr Pimenov <wachawo@gmail.com>
Maintainer-email: Aleksandr Pimenov <wachawo@gmail.com>
License: MIT License
Project-URL: Homepage, https://github.com/wachawo/checkcrontab
Project-URL: Repository, https://github.com/wachawo/checkcrontab
Project-URL: Documentation, https://github.com/wachawo/checkcrontab#readme
Project-URL: Bug Reports, https://github.com/wachawo/checkcrontab/issues
Keywords: crontab,cron,validation,syntax,checker,system,administration
Classifier: Development Status :: 5 - Production/Stable
Classifier: Intended Audience :: System Administrators
Classifier: Intended Audience :: Developers
Classifier: Topic :: System :: Systems Administration
Classifier: Topic :: Utilities
Classifier: License :: OSI Approved :: MIT License
Classifier: Programming Language :: Python :: 3
Classifier: Programming Language :: Python :: 3.7
Classifier: Programming Language :: Python :: 3.8
Classifier: Programming Language :: Python :: 3.9
Classifier: Programming Language :: Python :: 3.10
Classifier: Programming Language :: Python :: 3.11
Classifier: Programming Language :: Python :: 3.12
Classifier: Programming Language :: Python :: 3.13
Classifier: Operating System :: POSIX :: Linux
Classifier: Operating System :: Unix
Requires-Python: >=3.7
License-File: LICENSE
Provides-Extra: dev
Requires-Dist: pytest>=7.0.0; extra == "dev"
Requires-Dist: pytest-cov>=4.0.0; extra == "dev"
Requires-Dist: hypothesis>=6.97.0; extra == "dev"
Requires-Dist: coverage-badge>=1.1.0; extra == "dev"
Requires-Dist: flake8>=6.0.0; extra == "dev"
Requires-Dist: mypy>=1.0.0; extra == "dev"
Requires-Dist: ruff>=0.10.0; extra == "dev"
Requires-Dist: build>=0.10.0; extra == "dev"
Dynamic: license-file
